AUTHORS.rst
CONTRIBUTING.rst
HISTORY.rst
MANIFEST.in
README.md
setup.cfg
setup.py
docs/Makefile
docs/authors.rst
docs/conf.py
docs/contributing.rst
docs/history.rst
docs/index.rst
docs/installation.rst
docs/make.bat
docs/readme.rst
docs/usage.rst
fifteenrock/__init__.py
fifteenrock/constants.py
fifteenrock.egg-info/PKG-INFO
fifteenrock.egg-info/SOURCES.txt
fifteenrock.egg-info/dependency_links.txt
fifteenrock.egg-info/entry_points.txt
fifteenrock.egg-info/not-zip-safe
fifteenrock.egg-info/requires.txt
fifteenrock.egg-info/top_level.txt
fifteenrock/cli/__init__.py
fifteenrock/cli/cli.py
fifteenrock/cli/compute/__init__.py
fifteenrock/cli/compute/commands.py
fifteenrock/core/__init__.py
fifteenrock/core/compute_client.py
fifteenrock/core/core.py
fifteenrock/core/fr_notebook.py
fifteenrock/lib/__init__.py
fifteenrock/lib/helper.py
fifteenrock/lib/util.py
fifteenrock/template/__init__.py
fifteenrock/template/fifteenrock_project_main.py
fifteenrock/template/main.py
tests/__init__.py
tests/test_api.py
tests/test_fifteenrock.py