Metadata-Version: 1.1
Name: fifteenrock
Version: 0.1.91
Summary: Python client library for the 15Rock platform.
Home-page: https://github.com/RAbraham/fifteenrock
Author: Rajiv Abraham
Author-email: rajiv.abraham@15rock.com
License: UNKNOWN
Keywords: fifteenrock
Platform: UNKNOWN
Classifier: Development Status :: 2 - Pre-Alpha
Classifier: Intended Audience :: Developers
Classifier: Natural Language :: English
Classifier: Programming Language :: Python :: 3.6
Classifier: Programming Language :: Python :: 3.7
